attrs_mek/__init__.py
attrs_mek/key.py
attrs_mek/mek.py
attrs_mek/value.py
attrs_mek-0.0.5.dist-info/LICENSE
attrs_mek-0.0.5.dist-info/METADATA
attrs_mek-0.0.5.dist-info/WHEEL
attrs_mek-0.0.5.dist-info/top_level.txt
attrs_mek-0.0.5.dist-info/RECORD
