Metadata-Version: 2.1
Name: attrs-mek
Version: 0.0.5
Summary: Nested deserialization for attrs
Home-page: https://alrudolph.github.io/attrs-mek
Author: Alex Rudolph
Author-email: UNKNOWN
License: MIT
Platform: UNKNOWN
Requires-Dist: attrs
Requires-Dist: pytest
